mathml2omml/__init__.py
mathml2omml/op_dict.py
mathml2omml_as-0.1.0.dist-info/licenses/LICENSE
mathml2omml_as-0.1.0.dist-info/METADATA
mathml2omml_as-0.1.0.dist-info/WHEEL
mathml2omml_as-0.1.0.dist-info/top_level.txt
mathml2omml_as-0.1.0.dist-info/RECORD
