Metadata-Version: 2.4
Name: mathml2omml_as
Version: 0.1.0
Summary: Convert MathML to OMML (Allote.Software fork)
Home-page: https://github.com/AlloteSoftware/mathml2omml_as
Author: amedama41(patched by Allote.Software)
Keywords: MathML,OpenXML
Classifier: License :: OSI Approved :: MIT License
Classifier: Programming Language :: Python :: 3
Classifier: Topic :: Text Processing :: Markup :: XML
Requires-Python: >=3.7
License-File: LICENSE
Dynamic: author
Dynamic: classifier
Dynamic: description
Dynamic: home-page
Dynamic: keywords
Dynamic: license-file
Dynamic: requires-python
Dynamic: summary
